blackopt/__init__.py
blackopt/abc/__init__.py
blackopt/abc/problem.py
blackopt/abc/solution.py
blackopt/abc/solver.py
blackopt/algorithms/__init__.py
blackopt/algorithms/evo_multicore.py
blackopt/algorithms/evo_offspring_selection.py
blackopt/algorithms/evo_relevant_alleles.py
blackopt/algorithms/evolutionary.py
blackopt/algorithms/hill_climb.py
blackopt/algorithms/random_search.py
blackopt/algorithms/sasegasa.py
blackopt/algorithms/sasegasa_continuous.py
blackopt/algorithms/simulated_annealing.py
blackopt/blackopt.egg-info/PKG-INFO
blackopt/blackopt.egg-info/SOURCES.txt
blackopt/blackopt.egg-info/dependency_links.txt
blackopt/blackopt.egg-info/requires.txt
blackopt/blackopt.egg-info/top_level.txt
blackopt/compare.py
blackopt/config.py
blackopt/examples/__init__.py
blackopt/examples/launchers/_blackopt_workspace/reports/BumpyProblem 100 200@02-17_21-37-15/best_score.png
blackopt/examples/launchers/_blackopt_workspace/reports/BumpyProblem 100 200@11-30_10-15-46/best_score.png
blackopt/examples/launchers/compare_solvers_tsp.py
blackopt/examples/launchers/compare_tsp.py
blackopt/examples/launchers/launch_comparison_bumpy.py
blackopt/examples/launchers/launch_comparison_step.py
blackopt/examples/launchers/solve_tsp.py
blackopt/examples/launchers/solve_tsp_long.py
blackopt/examples/problems/__init__.py
blackopt/examples/problems/bumpy.py
blackopt/examples/problems/stepwise.py
blackopt/examples/problems/tsp/__init__.py
blackopt/examples/problems/tsp/city.py
blackopt/examples/problems/tsp/tsp.py
blackopt/exceptions.py
blackopt/log.py
blackopt/persistence.py
blackopt/util/document.py
blackopt/util/test.py
blackopt/util/timeout.py
blackopt-0.28.dist-info/WHEEL
blackopt-0.28.dist-info/METADATA
blackopt-0.28.dist-info/RECORD
