Metadata-Version: 2.1
Name: blackopt
Version: 0.28
Summary: black box optimization library
License: MIT
Author: Ilya Kamen
Author-email: ikamenshchikov@gmail.com
Requires-Python: >=3.6,<4.0
Classifier: License :: OSI Approved :: MIT License
Classifier: Programming Language :: Python :: 3
Classifier: Programming Language :: Python :: 3.6
Classifier: Programming Language :: Python :: 3.7
Classifier: Programming Language :: Python :: 3.8
Classifier: Programming Language :: Python :: 3.9
Requires-Dist: ilya-ezplot (>=0.11,<0.12)
Requires-Dist: numpy (>=1.18.1,<2.0.0)
Requires-Dist: pathos (>=0.2.5,<0.3.0)
Requires-Dist: structlog (>=20.1.0,<21.0.0)
